<?xml version="1.0" encoding="utf-8" ?>
<LanguageData>

  <AnimalInsanitySingle>Een {0} is gek geworden. Het valt iedereen aan, die hij ziet.</AnimalInsanitySingle>
  <AnimalInsanityMultiple>Een psychische golf rolt over het landschap. De kolonisten mankeert niets, maar....\n\nHet schijnt, dat een paar {0}s door zijn gedraaid.</AnimalInsanityMultiple>

  <CropBlight>Een misterieuze plaag heeft je gewassen vernietigd.</CropBlight>

  <EclipseIncident>Een van de manen van de planeet schuift voor de zon. Een zonsverduistering is begonnen.</EclipseIncident>

  <MiracleHeal>{0} is op wonderbaarlijke wijze hersteld!</MiracleHeal>

  
  <!-- Enemy raids -->
  <EnemyRaidWalkIn>Een groep {0} van {1} zijn in de buurt.</EnemyRaidWalkIn>
  <EnemyRaidEdgeDrop>Een groep {0} van {1} zijn vanuit hun orbitale baan geland.</EnemyRaidEdgeDrop>
  <EnemyRaidCenterDrop>Een groep {0} van {1} zijn vanuit hun orbitale baan direct op de kolonie geland!</EnemyRaidCenterDrop>
  <EnemyRaidStageThenAttack>Zij zullen zich voor hun aanval voorbereiden.\n\nBereidt de verdediging voor, of val ze zelf aan.</EnemyRaidStageThenAttack>
  <EnemyRaidImmediateAttack>Ze vallen direct aan.</EnemyRaidImmediateAttack>
  <EnemyRaidBesiege>Het ziet er naar uit dat ze de kolonie willen belegeren.</EnemyRaidBesiege>


  <!-- Friendly raids -->
  <FriendlyRaidWalkIn>Een groep vriendelijke {0} van {1} zijn in de buurt.</FriendlyRaidWalkIn>
  <FriendlyRaidEdgeDrop>Een groep vriendelijke {0} van {1} zijn vanuit hun orbitale baan geland.</FriendlyRaidEdgeDrop>
  <FriendlyRaidCenterDrop>Een groep vriendelijke {0} van {1} zijn vanuit hun orbitale baan direct op de kolonie geland!</FriendlyRaidCenterDrop>
  <FriendlyRaidStageThenAttack>Ze moeten zich even voorbereiden, voordat ze je kunnen helpen.</FriendlyRaidStageThenAttack>
  <FriendlyRaidImmediateAttack>Ze kunnen je direct helpen.</FriendlyRaidImmediateAttack>
  <FriendlyRaidBesiege>Het ziet er naar uit, dat ze met belegeringsvoorwerpen willen helpen.</FriendlyRaidBesiege>

 <RefugeePodCrash>Je hebt een neerstortende noodcapsule gehoord.\n\nAls iemand de inslag heeft overleeft, zal hij/zij zwaar gewond zijn.</RefugeePodCrash>

  <CargoPodCrash>Je hebt een neerstortende vooraadcapsule gehoord.\n\nMisschien vind je wat nuttigs in het wrak.</CargoPodCrash>

  <AnElectricalConduit>een stroomdraad</AnElectricalConduit>
  <AWallsPowerConduit>een wandstroomdraad</AWallsPowerConduit>
  <ShortCircuit>Een fout in {0} heeft kortsluiting veroorzaakt.\n\nDe {1} watt aan energie opgeslagen in de verbonden batterijen is verloren gegaan.</ShortCircuit>
  <ShortCircuitWasLarge>Deze kortsluiting heeft een grote explosie veroorzaakt.</ShortCircuitWasLarge>
  <ShortCircuitWasHuge>De explosie van deze kortsluiting was enorm. Wow.</ShortCircuitWasHuge>

   <LetterSolarFlare>Een zonnestorm is begonnen.\n\nDDe sterke straling maakt alle electrische apparaten onbruikbaar.\n\nHet zal over een paar dagen over zijn.</LetterSolarFlare>

  <TraderArrival>Een handelsschip is in de buurt.\n\nHet heet {0} en is {1}.</TraderArrival>

   <SingleTravelerPassing>Een {0} van {1} is op doorreis. HECAP heet {2}.</SingleTravelerPassing>
  <GroupTravelersPassing>Een groep van {0} is op doorreis.</GroupTravelersPassing>

  <SingleVisitorArrives>Een {0} van {1} bezoekt de kolonie.\n\nHECAP heet {2}.</SingleVisitorArrives>
  <GroupVisitorsArrive>>Een groep van {0} bezoekt de kolonie.</GroupVisitorsArrive>
  <VisitorsLeaving>De bezoekers van {0} verlaten de kolonie.</VisitorsLeaving>

  <WandererJoin>Een {0} die NAME heet is aangekomen en treedt bij de kolonie. HECAP is een {1}.</WandererJoin>
  
    <!-- Crashed ship part-->
  <SpaceshipPartCrash>Een groot stuk van een ruimteschip is in de buurt ingeslagen.\n\nJe kolonisten voelen instinctief dat er iets slechts aan de hand is. Aan boord moet zich een AI bevinden met psychische krachten. En deze AI is hen niet vriendelijk gezind.\n\nVerzet je zo goed mogenlijk.</SpaceshipPartCrash>
  <MessageAnimalInsanityPulse>De antieke structuur heeft een psychische impuls uitgezonden, die de dieren in de omgeving gek heeft gemaakt.</MessageAnimalInsanityPulse>
  <LetterShipPartDroveColonistInsane>Het neergestorte schipsdeel heeft een psychische impuls uitgezonden, die de kolonisten {0} gek heeft gemaakt.</LetterShipPartDroveColonistInsane>
  <AwokeDaysAgo>Wakker sinds {0} dagen</AwokeDaysAgo>
  <PsychicDroneLevel>Niveau van het psychische brommen: {0}</PsychicDroneLevel>
  <PsychicDroneLevelLow>een beetje</PsychicDroneLevelLow>
  <PsychicDroneLevelMedium>gemiddeld</PsychicDroneLevelMedium>
  <PsychicDroneLevelHigh>hoog</PsychicDroneLevelHigh>
  <PsychicDroneLevelExtreme>extreem</PsychicDroneLevelExtreme>
  <LetterPsychicDroneLevelIncreased>Het neergestorte schipsdeel heeft zijn psychische signaal versterkt. Ieder menselijk wezen in de omgeving voelt zich nog sterker beïnvloed, angstig en paranoïde.</LetterPsychicDroneLevelIncreased>
  
  <!-- Agent revealed -->
  <LetterAgentRevealed>{0} is als een agent van je tegenstander {1} ontmaskerd.\n\nHij probeert te ontkomen..</LetterAgentRevealed>
  
  <!-- Distant psychic drone -->
  <LetterIncidentPsychicDrone>Een sterke psychische dreun hamert op de hoofden van {0} kolonisten!\n\nEen zeer geavanceerde machine ontwaakt en zend een golf uit, op een frequentie die blijkbaar alleen {0} als slecht ervaart. De stemming van je kolonisten zal de komende dagen flink wat slechter zijn.</LetterIncidentPsychicDrone>
  
</LanguageData>