<?xml version="1.0" encoding="utf-8" ?>
<LanguageData>
	
	<AridShrubland.label>Steppe</AridShrubland.label>
	<AridShrubland.description>Een warm, droog gebied, maar niet genoeg om tot een woestijn te worden benoemd. Grote open vlaktes bedekt met gras, onderbroken door hier en daar een bosje. Alleen geharde planten overleven het hier en er zijn redelijk wat dieren in de omgeving.</AridShrubland.description>
	
	<Desert.label>Woestijn</Desert.label>
	<Desert.description>Een zeer droog en heet gebied, waar erg weinig dieren en planten zijn.</Desert.description>
	<ExtremeDesert.label>Extreme woestijn</ExtremeDesert.label>
	<ExtremeDesert.description>Een extreem droog en heet gebied, waar nauwelijks dieren zijn. De immense hitte en zeldzame planten maken het erg moeilijk om hier te overleven, zelfs voor goed aangepaste dieren.</ExtremeDesert.description>
</LanguageData>
