<?xml version="1.0" encoding="UTF-8"?>
<LanguageData>
  
  <!-- EN: orbital trader arrival -->
  <OrbitalTraderArrival.label>ruimtehandelaar</OrbitalTraderArrival.label>
  
  <!-- EN: friendly raid -->
  <RaidFriendly.label>bevriende troepen</RaidFriendly.label>
  
  <!-- EN: ship chunk drop -->
  <ShipChunkDrop.label>neergestort scheepsdeel</ShipChunkDrop.label>
  
  <!-- EN: man in black -->
  <StrangerInBlackJoin.label>mysterieuze vreemdeling</StrangerInBlackJoin.label>
  <!-- EN: Man in black -->
  <StrangerInBlackJoin.letterLabel>Mysterieuze vreemdeling</StrangerInBlackJoin.letterLabel>
  <!-- EN: Sensing trouble, a mysterious [PAWN_kind] has arrived.\n\nWill [PAWN_pronoun] be able to set things right in these parts? -->
  <StrangerInBlackJoin.letterText>Een mysterieuze [PAWN_kind] voelde zich geroepen door een slecht voorgevoel.\n\nZal [PAWN_pronoun] de kolonie weer op het op weg kunnen helpen?</StrangerInBlackJoin.letterText>
  
  <!-- EN: trader caravan arrival -->
  <TraderCaravanArrival.label>handelskaravaan</TraderCaravanArrival.label>
  
  <!-- EN: traveler group -->
  <TravelerGroup.label>reisgroep</TravelerGroup.label>
  
  <!-- EN: visitor group -->
  <VisitorGroup.label>bezoekersgroep</VisitorGroup.label>
  
</LanguageData>