<?xml version="1.0" encoding="UTF-8"?>
<LanguageData>
  
  <!-- EN: Create beautiful works of art from raw materials. -->
  <Art.description>Maak prachtige kunstwerken van ruwe materialen.</Art.description>
  <!-- EN: art -->
  <Art.gerundLabel>beeldhouwen</Art.gerundLabel>
  <!-- EN: art -->
  <Art.labelShort>kunst</Art.labelShort>
  <!-- EN: Artist -->
  <Art.pawnLabel>Kunstenaar</Art.pawnLabel>
  <!-- EN: Do art at -->
  <Art.verb>Beeldhouwen</Art.verb>
  
  <!-- EN: Unskilled and easy tasks. Release prisoners and flick switches on machines. -->
  <BasicWorker.description>Ongetrainde en eenvoudige taken. Laat gevangenen vrij en zet machines aan en uit.</BasicWorker.description>
  <!-- EN: dealing with -->
  <BasicWorker.gerundLabel>afhandelen</BasicWorker.gerundLabel>
  <!-- EN: basic -->
  <BasicWorker.labelShort>basis</BasicWorker.labelShort>
  <!-- EN: Worker -->
  <BasicWorker.pawnLabel>Werker</BasicWorker.pawnLabel>
  <!-- EN: Deal with -->
  <BasicWorker.verb>Handel af</BasicWorker.verb>
  
  <!-- EN: Clear snow and clean the floor in the home area. -->
  <Cleaning.description>Sneeuwruimen en de vloer schoonmaken in het thuisgebied</Cleaning.description>
  <!-- EN: cleaning -->
  <Cleaning.gerundLabel>schoonmaken</Cleaning.gerundLabel>
  <!-- EN: clean -->
  <Cleaning.labelShort>   Schoonmaken</Cleaning.labelShort><!-- Manual justification for readability. -->
  <!-- EN: Cleaner -->
  <Cleaning.pawnLabel>Schoonmaker</Cleaning.pawnLabel>
  <!-- EN: Clean -->
  <Cleaning.verb>Maak schoon</Cleaning.verb>
  
  <!-- EN: Build things that you've designated, and fix damaged or broken-down buildings. -->
  <Construction.description>Bouw dingen die je hebt gemarkeerd, en repareer beschadigde gebouwen.</Construction.description>
  <!-- EN: constructing -->
  <Construction.gerundLabel>bouwen</Construction.gerundLabel>
  <!-- EN: construct -->
  <Construction.labelShort>bouwen</Construction.labelShort>
  <!-- EN: Constructor -->
  <Construction.pawnLabel>Bouwvakker</Construction.pawnLabel>
  <!-- EN: Construct -->
  <Construction.verb>Bouw</Construction.verb>
  
  <!-- EN: Prepare meals and butcher meat. -->
  <Cooking.description>Kook maaltijden en slacht vlees</Cooking.description>
  <!-- EN: cooking -->
  <Cooking.gerundLabel>koken</Cooking.gerundLabel>
  <!-- EN: cook -->
  <Cooking.labelShort>koken</Cooking.labelShort>
  <!-- EN: Cook -->
  <Cooking.pawnLabel>Kok</Cooking.pawnLabel>
  <!-- EN: Cook -->
  <Cooking.verb>Kook</Cooking.verb>
  
  <!-- EN: Do general low-skilled labor at work stations. This includes stonecutting, smelting, and more. -->
  <Crafting.description>Algemeen laaggeschoolde arbeid aan werktafels, zoals: steenhouwen, smelten en meer.</Crafting.description>
  <!-- EN: crafting -->
  <Crafting.gerundLabel>maken</Crafting.gerundLabel>
  <!-- EN: craft -->
  <Crafting.labelShort>handwerk</Crafting.labelShort>
  <!-- EN: Crafter -->
  <Crafting.pawnLabel>Handwerker</Crafting.pawnLabel>
  <!-- EN: Craft at -->
  <Crafting.verb>maak</Crafting.verb>
  
  <!-- EN: Treat the sick, bring them food, cheer them up, and perform assigned surgeries. Doctors will care for both colonists and prisoners. -->
  <Doctor.description>Verzorg zieken, breng ze eten, vrolijk ze op en voer toegewezen operaties uit. Dokters verzorgen zowel kolonisten als gevangenen.</Doctor.description>
  <!-- EN: doctoring -->
  <Doctor.gerundLabel>verzorgen</Doctor.gerundLabel>
  <!-- EN: doctor -->
  <Doctor.labelShort>dokter</Doctor.labelShort>
  <!-- EN: Doctor -->
  <Doctor.pawnLabel>Dokter</Doctor.pawnLabel>
  <!-- EN: Care for -->
  <Doctor.verb>Verzorg</Doctor.verb>
  
  <!-- EN: Extinguish fires in the colony. -->
  <Firefighter.description>Blus branden in de kolonie.</Firefighter.description>
  <!-- EN: firefighting -->
  <Firefighter.gerundLabel>brandblussen</Firefighter.gerundLabel>
  <!-- EN: firefight -->
  <Firefighter.labelShort>blussen</Firefighter.labelShort>
  <!-- EN: Firefighter -->
  <Firefighter.pawnLabel>Brandweerman</Firefighter.pawnLabel>
  <!-- EN: Extinguish -->
  <Firefighter.verb>Blus</Firefighter.verb>
  
  <!-- EN: Plant seeds, harvest crops, and forage for wild plants. -->
  <Growing.description>Zaai zaden, oogst gewas en foerageer wilde planten.</Growing.description>
  <!-- EN: growing -->
  <Growing.gerundLabel>landbouwen</Growing.gerundLabel>
  <!-- EN: grow -->
  <Growing.labelShort>landbouwen</Growing.labelShort>
  <!-- EN: Grower -->
  <Growing.pawnLabel>Landbouwer</Growing.pawnLabel>
  <!-- EN: Grow -->
  <Growing.verb>Verbouw</Growing.verb>
  
  <!-- EN: Tame, train, harvest resources from and slaughter animals. -->
  <Handling.description>Tem, train, oogst grondstoffen van en slacht dieren.</Handling.description>
  <!-- EN: handling -->
  <Handling.gerundLabel>dieren verzorgen</Handling.gerundLabel>
  <!-- EN: handle -->
  <Handling.labelShort>dierenzorg</Handling.labelShort>
  <!-- EN: Handler -->
  <Handling.pawnLabel>Dierenverzorger</Handling.pawnLabel>
  <!-- EN: Handle -->
  <Handling.verb>Verzorg dieren</Handling.verb>
  
  <!-- EN: Carry things to where they need to be. -->
  <Hauling.description>Sleep dingen naar hun bestemming.</Hauling.description>
  <!-- EN: hauling -->
  <Hauling.gerundLabel>slepen</Hauling.gerundLabel>
  <!-- EN: haul -->
  <Hauling.labelShort>slepen</Hauling.labelShort>
  <!-- EN: Hauler -->
  <Hauling.pawnLabel>Sleper</Hauling.pawnLabel>
  <!-- EN: Haul -->
  <Hauling.verb>Sleep</Hauling.verb>
  
  <!-- EN: Kill animals which are designated to be hunted. -->
  <Hunting.description>Jaag op dieren die aangemerkt zijn om gejaagd te worden.</Hunting.description>
  <!-- EN: hunting -->
  <Hunting.gerundLabel>jagen</Hunting.gerundLabel>
  <!-- EN: hunt -->
  <Hunting.labelShort>jagen</Hunting.labelShort>
  <!-- EN: Hunter -->
  <Hunting.pawnLabel>Jager</Hunting.pawnLabel>
  <!-- EN: Hunt -->
  <Hunting.verb>Jaag</Hunting.verb>
  
  <!-- EN: Digging and drilling. -->
  <Mining.description>Delven en boren.</Mining.description>
  <!-- EN: mining -->
  <Mining.gerundLabel>delven</Mining.gerundLabel>
  <!-- EN: mine -->
  <Mining.labelShort>delven</Mining.labelShort>
  <!-- EN: Miner -->
  <Mining.pawnLabel>Delver</Mining.pawnLabel>
  <!-- EN: Mine -->
  <Mining.verb>Delf</Mining.verb>
  
  <!-- EN: Go to a medical bed for treatment if you have an immediately life-threatening health condition. -->
  <Patient.description>Ga naar een ziekenbed voor behandeling als je een direct levensbedreigende medische conditie hebt.</Patient.description>
  <!-- EN: patienting -->
  <Patient.gerundLabel>patiënt</Patient.gerundLabel>
  <!-- EN: patient -->
  <Patient.labelShort>patiënt</Patient.labelShort>
  <!-- EN: Patient -->
  <Patient.pawnLabel>Patiënt</Patient.pawnLabel>
  <!-- EN: Become patient -->
  <Patient.verb>Word patient</Patient.verb>
  
  <!-- EN: Rest in bed to recuperate from not-immediately-life-threatening medical problems. -->
  <PatientBedRest.description>Rust in bed om te herstellen van niet direct levensbedreigende medische condities.</PatientBedRest.description>
  <!-- EN: resting in bed -->
  <PatientBedRest.gerundLabel>in bed uitrusten</PatientBedRest.gerundLabel>
  <!-- EN: bed rest -->
  <PatientBedRest.labelShort>bedrust</PatientBedRest.labelShort>
  <!-- EN: Bed rester -->
  <PatientBedRest.pawnLabel>bedruster</PatientBedRest.pawnLabel>
  <!-- EN: Become patient -->
  <PatientBedRest.verb>Word patiënt</PatientBedRest.verb>
  
  <!-- EN: Cut or harvest plants as designated. -->
  <PlantCutting.description>Wied of oogst planten zoals aangemerkt.</PlantCutting.description>
  <!-- EN: plant cutting -->
  <PlantCutting.gerundLabel>planten wieden</PlantCutting.gerundLabel>
  <!-- EN: plant cut -->
  <PlantCutting.labelShort>wieden</PlantCutting.labelShort>
  <!-- EN: Plant cutter -->
  <PlantCutting.pawnLabel>tuinman</PlantCutting.pawnLabel>
  <!-- EN: Cut -->
  <PlantCutting.verb>Wied planten</PlantCutting.verb>
  
  <!-- EN: Perform research work. -->
  <Research.description>Doe onderzoek.</Research.description>
  <!-- EN: researching -->
  <Research.gerundLabel>onderzoeken</Research.gerundLabel>
  <!-- EN: research -->
  <Research.labelShort>onderzoek</Research.labelShort>
  <!-- EN: Researcher -->
  <Research.pawnLabel>Onderzoeker</Research.pawnLabel>
  <!-- EN: Research at -->
  <Research.verb>Doe onderzoek naar</Research.verb>
  
  <!-- EN: Create weapons and tools from raw materials, either as a blacksmith or by machining. -->
  <Smithing.description>Maak wapens en gereedschap van ruwe grondstoffen, als smid of aan de machinetafel.</Smithing.description>
  <!-- EN: smithing -->
  <Smithing.gerundLabel>smeden</Smithing.gerundLabel>
  <!-- EN: smith -->
  <Smithing.labelShort>smeden</Smithing.labelShort>
  <!-- EN: Smith -->
  <Smithing.pawnLabel>Smid</Smithing.pawnLabel>
  <!-- EN: Smith at -->
  <Smithing.verb>Smeed bij</Smithing.verb>
  
  <!-- EN: Create apparel from raw materials. -->
  <Tailoring.description>Maak kleding van ruwe grondstoffen.</Tailoring.description>
  <!-- EN: tailoring -->
  <Tailoring.gerundLabel>kleermaken</Tailoring.gerundLabel>
  <!-- EN: tailor -->
  <Tailoring.labelShort>kleermaken</Tailoring.labelShort>
  <!-- EN: Tailor -->
  <Tailoring.pawnLabel>Kleermaker</Tailoring.pawnLabel>
  <!-- EN: Tailor at -->
  <Tailoring.verb>Kleermaken bij</Tailoring.verb>
  
  <!-- EN: Manage, feed, chat with, and recruit prisoners. -->
  <Warden.description>Bewaak, geef te eten, praat met en rekruteer gevangenen.</Warden.description>
  <!-- EN: wardening -->
  <Warden.gerundLabel>bewaken</Warden.gerundLabel>
  <!-- EN: warden -->
  <Warden.labelShort>bewaken</Warden.labelShort>
  <!-- EN: Warden -->
  <Warden.pawnLabel>Bewaker</Warden.pawnLabel>
  <!-- EN: Handle -->
  <Warden.verb>Bewaak</Warden.verb>
  
</LanguageData>